movie_reviews/__init__.py
movie_reviews/combine.py
movie_reviews/generate.py
movie_reviews/data/combined_movie_reviews.csv
movie_reviews-0.0.2.dist-info/LICENSE.txt
movie_reviews-0.0.2.dist-info/METADATA
movie_reviews-0.0.2.dist-info/WHEEL
movie_reviews-0.0.2.dist-info/top_level.txt
movie_reviews-0.0.2.dist-info/RECORD
