Metadata-Version: 2.1
Name: movie-reviews
Version: 0.0.2
Summary: Generate sample movie reviews data for data science projects
Home-page: https://github.com/lornamariak/movie-reviews
Author: Lorna Aine
Author-email: lorna.aine@duke.edu
License: MIT
Classifier: Development Status :: 3 - Alpha
Classifier: Intended Audience :: Education
Classifier: License :: OSI Approved :: MIT License
Classifier: Natural Language :: English
Classifier: Programming Language :: Python :: 3
Classifier: Programming Language :: Python :: 3
Classifier: Programming Language :: Python :: 3.7
Classifier: Programming Language :: Python :: 3.8
Classifier: Programming Language :: Python :: 3.9
Classifier: Programming Language :: Python :: 3.10
Classifier: Programming Language :: Python :: 3.11
Classifier: Programming Language :: Python :: 3 :: Only
Requires-Python: >=3.6
License-File: LICENSE.txt
Requires-Dist: pandas (>=1.4.4)
